bitbangrelay/__init__.py
bitbangrelay/__main__.py
bitbangrelay/relay.py
bitbangrelay-0.1.0.dist-info/Apache-2.0.txt
bitbangrelay-0.1.0.dist-info/CC-BY-4.0.txt
bitbangrelay-0.1.0.dist-info/CC0-1.0.txt
bitbangrelay-0.1.0.dist-info/METADATA
bitbangrelay-0.1.0.dist-info/WHEEL
bitbangrelay-0.1.0.dist-info/entry_points.txt
bitbangrelay-0.1.0.dist-info/top_level.txt
bitbangrelay-0.1.0.dist-info/RECORD
