Metadata-Version: 2.1
Name: bitbangrelay
Version: 0.1.0
Summary: Simple tool for controlling USB bitbang relay boards.
Home-page: https://github.com/SanCloudLtd/bitbangrelay
Maintainer: Paul Barker
Maintainer-email: paul.barker@sancloud.com
License: Apache-2.0 AND CC-BY-4.0 AND CC0-1.0
Platform: any
Classifier: Programming Language :: Python :: 3
Classifier: License :: OSI Approved :: Apache Software License
Classifier: Operating System :: OS Independent
Requires-Python: >=3.6
License-File: LICENSES/Apache-2.0.txt
License-File: LICENSES/CC-BY-4.0.txt
License-File: LICENSES/CC0-1.0.txt
Requires-Dist: pyyaml
Requires-Dist: pylibftdi
